{
  "version": "director-room-v1-2026-06-05",
  "episode_id": "09",
  "assets": [
    {
      "asset_id": "ch_shen_weisang",
      "asset_type": "character",
      "file_path": "assets/placeholders/ch_shen_weisang.png",
      "status": "missing",
      "prompt_hint_zh": "17岁人族猎户兼旧驿后裔，灰褐猎衣、草药青内层、旧皮护腕、猎弓、短刀、路线包；左肩旧伤必须持续可见。",
      "prompt_hint_en": "Grey-brown hunter clothing, herb-green inner layer, old leather wrist guards, bow, short knife and route pack; his injured left shoulder remains visible and limiting.",
      "comfyui_role": "reference_image",
      "usage": [
        "SC001-SH001",
        "SC001-SH002",
        "SC001-SH003",
        "SC001-SH004",
        "SC001-SH005",
        "SC001-SH006",
        "SC001-SH007",
        "SC001-SH008",
        "SC001-SH009",
        "SC001-SH010",
        "SC002-SH001",
        "SC002-SH002",
        "SC002-SH003",
        "SC002-SH004",
        "SC002-SH005",
        "SC002-SH006",
        "SC002-SH007",
        "SC002-SH008",
        "SC002-SH009",
        "SC002-SH010"
      ],
      "continuity_refs": [
        "CH_SHEN_WEISANG"
      ]
    },
    {
      "asset_id": "ch_yan_nanzhi",
      "asset_type": "character",
      "file_path": "assets/placeholders/ch_yan_nanzhi.png",
      "status": "missing",
      "prompt_hint_zh": "18岁人族旧帝国皇室旁支，黑发红线、冷灰/雾紫流亡外袍、隐藏月白玉片与血牒；逃亡中仍保持挺直礼法姿态。",
      "prompt_hint_en": "Human imperial remnant, black hair tied with a red thread, cold grey or mist-purple fugitive robe, hidden moon-white jade and blood record; upright ritual posture even while fleeing.",
      "comfyui_role": "reference_image",
      "usage": [
        "SC001-SH001",
        "SC001-SH002",
        "SC001-SH003",
        "SC001-SH004",
        "SC001-SH005",
        "SC001-SH006",
        "SC001-SH007",
        "SC001-SH008",
        "SC001-SH009",
        "SC001-SH010",
        "SC002-SH001",
        "SC002-SH002",
        "SC002-SH003",
        "SC002-SH004",
        "SC002-SH005",
        "SC002-SH006",
        "SC002-SH007",
        "SC002-SH008",
        "SC002-SH009",
        "SC002-SH010"
      ],
      "continuity_refs": [
        "CH_YAN_NANZHI"
      ]
    },
    {
      "asset_id": "ch_lu_qingli",
      "asset_type": "character",
      "file_path": "assets/placeholders/ch_lu_qingli.png",
      "status": "missing",
      "prompt_hint_zh": "墙下无姓混裔少女，灰蓝短袄、陶土色内层、碎陶护符、黑市通行木牌、腰间窄刀、耳后细鳞痕。",
      "prompt_hint_en": "Wall-foot nameless hybrid girl, grey-blue short jacket, clay inner layer, broken pottery charm, black-market wooden pass, narrow knife and faint scales behind the ear.",
      "comfyui_role": "reference_image",
      "usage": [
        "SC001-SH001",
        "SC001-SH002",
        "SC001-SH003",
        "SC001-SH004",
        "SC001-SH005",
        "SC001-SH006",
        "SC001-SH007",
        "SC001-SH008",
        "SC001-SH009",
        "SC001-SH010",
        "SC002-SH001",
        "SC002-SH002",
        "SC002-SH003",
        "SC002-SH004",
        "SC002-SH005",
        "SC002-SH006",
        "SC002-SH007",
        "SC002-SH008",
        "SC002-SH009",
        "SC002-SH010"
      ],
      "continuity_refs": [
        "CH_LU_QINGLI"
      ]
    },
    {
      "asset_id": "ch_lu_mi",
      "asset_type": "character",
      "file_path": "assets/placeholders/ch_lu_mi.png",
      "status": "missing",
      "prompt_hint_zh": "北境鹿族伤者/萨满线索人物，鹿耳短角、骨饰、血盐袋、药草袋、骨笛；伤势与求救状态要清楚。",
      "prompt_hint_en": "Northern deer-clan wounded guide, deer ears and short antlers, bone ornaments, blood-salt pouch, herb pouch and bone flute; injury and rescue state must read clearly.",
      "comfyui_role": "reference_image",
      "usage": [
        "SC002-SH001",
        "SC002-SH002",
        "SC002-SH003",
        "SC002-SH004",
        "SC002-SH005",
        "SC002-SH006",
        "SC002-SH007",
        "SC002-SH008",
        "SC002-SH009",
        "SC002-SH010",
        "SC003-SH001",
        "SC003-SH002",
        "SC003-SH003",
        "SC003-SH004",
        "SC003-SH005",
        "SC003-SH006",
        "SC003-SH007",
        "SC003-SH008",
        "SC003-SH009",
        "SC003-SH010"
      ],
      "continuity_refs": [
        "CH_LU_MI"
      ]
    },
    {
      "asset_id": "ch_army_scouts",
      "asset_type": "character",
      "file_path": "assets/placeholders/ch_army_scouts.png",
      "status": "missing",
      "prompt_hint_zh": "甲军府斥候，冷兵器、军府封锁姿态、边墙战区追击纪律清楚。",
      "prompt_hint_en": "Military office scouts with cold weapons, blockade posture and disciplined frontier pursuit.",
      "comfyui_role": "reference_image",
      "usage": [
        "SC002-SH001",
        "SC002-SH002",
        "SC002-SH003",
        "SC002-SH004",
        "SC002-SH005",
        "SC002-SH006",
        "SC002-SH007",
        "SC002-SH008",
        "SC002-SH009",
        "SC002-SH010",
        "SC003-SH001",
        "SC003-SH002",
        "SC003-SH003",
        "SC003-SH004",
        "SC003-SH005",
        "SC003-SH006",
        "SC003-SH007",
        "SC003-SH008",
        "SC003-SH009",
        "SC003-SH010"
      ],
      "continuity_refs": [
        "CH_ARMY_SCOUTS"
      ]
    },
    {
      "asset_id": "ch_northern_raiders",
      "asset_type": "character",
      "file_path": "assets/placeholders/ch_northern_raiders.png",
      "status": "missing",
      "prompt_hint_zh": "北境南压队伍，不能画成无脑兽潮；要有人与共生兽、冻伤、迁徙与求生痕迹。",
      "prompt_hint_en": "Northern pressure group, not a mindless beast horde; show people, symbiotic beasts, frost injuries, migration and survival traces.",
      "comfyui_role": "reference_image",
      "usage": [
        "SC003-SH001",
        "SC003-SH002",
        "SC003-SH003",
        "SC003-SH004",
        "SC003-SH005",
        "SC003-SH006",
        "SC003-SH007",
        "SC003-SH008",
        "SC003-SH009",
        "SC003-SH010"
      ],
      "continuity_refs": [
        "CH_NORTHERN_RAIDERS"
      ]
    },
    {
      "asset_id": "loc_minggu_bone_ridge",
      "asset_type": "location",
      "file_path": "assets/placeholders/loc_minggu_bone_ridge.png",
      "status": "missing",
      "prompt_hint_zh": "半埋骨骸、风蚀骨孔、雪坑、冰蓝火、骨笛和北境迁徙痕迹。",
      "prompt_hint_en": "location reference for Minggu Bone Ridge",
      "comfyui_role": "reference_image",
      "usage": [
        "SC001-SH001",
        "SC001-SH002",
        "SC001-SH003",
        "SC001-SH004",
        "SC001-SH005",
        "SC001-SH006",
        "SC001-SH007",
        "SC001-SH008",
        "SC001-SH009",
        "SC001-SH010",
        "SC002-SH001",
        "SC002-SH002",
        "SC002-SH003",
        "SC002-SH004",
        "SC002-SH005",
        "SC002-SH006",
        "SC002-SH007",
        "SC002-SH008",
        "SC002-SH009",
        "SC002-SH010"
      ],
      "continuity_refs": [
        "LOC_MINGGU_BONE_RIDGE"
      ]
    },
    {
      "asset_id": "loc_bone_flute_valley_mouth",
      "asset_type": "location",
      "file_path": "assets/placeholders/loc_bone_flute_valley_mouth.png",
      "status": "missing",
      "prompt_hint_zh": "谷口夹击空间，甲军斥候与北境掠粮派同时逼近。",
      "prompt_hint_en": "location reference for Bone Flute valley mouth",
      "comfyui_role": "reference_image",
      "usage": [
        "SC003-SH001",
        "SC003-SH002",
        "SC003-SH003",
        "SC003-SH004",
        "SC003-SH005",
        "SC003-SH006",
        "SC003-SH007",
        "SC003-SH008",
        "SC003-SH009",
        "SC003-SH010"
      ],
      "continuity_refs": [
        "LOC_BONE_FLUTE_VALLEY_MOUTH"
      ]
    },
    {
      "asset_id": "loc_outer_wall_ruined_beacon",
      "asset_type": "location",
      "file_path": "assets/placeholders/loc_outer_wall_ruined_beacon.png",
      "status": "missing",
      "prompt_hint_zh": "暮色废烽燧、盟书印记、冻裂旧兵器和北境旧誓线索。",
      "prompt_hint_en": "location reference for ruined beacon outside the wall",
      "comfyui_role": "reference_image",
      "usage": [
        "SC004-SH001",
        "SC004-SH002",
        "SC004-SH003",
        "SC004-SH004",
        "SC004-SH005",
        "SC004-SH006",
        "SC004-SH007",
        "SC004-SH008",
        "SC004-SH009",
        "SC004-SH010"
      ],
      "continuity_refs": [
        "LOC_OUTER_WALL_RUINED_BEACON"
      ]
    },
    {
      "asset_id": "prop_moon_white_jade",
      "asset_type": "prop",
      "file_path": "assets/placeholders/prop_moon_white_jade.png",
      "status": "missing",
      "prompt_hint_zh": "晏南枝隐藏身份的月白玉片，火光或旧驿反应中显出日月纹。",
      "prompt_hint_en": "moon-white jade piece that exposes Yan Nanzhi's identity when firelight or relay-stone reaction reveals sun-moon markings",
      "comfyui_role": "reference_image",
      "usage": [
        "SC001-SH001",
        "SC001-SH002",
        "SC001-SH003",
        "SC001-SH004",
        "SC001-SH005",
        "SC001-SH006",
        "SC001-SH007",
        "SC001-SH008",
        "SC001-SH009",
        "SC001-SH010",
        "SC004-SH001",
        "SC004-SH002",
        "SC004-SH003",
        "SC004-SH004",
        "SC004-SH005",
        "SC004-SH006",
        "SC004-SH007",
        "SC004-SH008",
        "SC004-SH009",
        "SC004-SH010"
      ],
      "continuity_refs": [
        "PROP_MOON_WHITE_JADE"
      ]
    },
    {
      "asset_id": "prop_bone_flute",
      "asset_type": "prop",
      "file_path": "assets/placeholders/prop_bone_flute.png",
      "status": "missing",
      "prompt_hint_zh": "鹿弥和北境求救/停兽逻辑的核心道具。",
      "prompt_hint_en": "bone flute used by Lu Mi and northern rescue or beast-calming logic",
      "comfyui_role": "reference_image",
      "usage": [
        "SC001-SH001",
        "SC001-SH002",
        "SC001-SH003",
        "SC001-SH004",
        "SC001-SH005",
        "SC001-SH006",
        "SC001-SH007",
        "SC001-SH008",
        "SC001-SH009",
        "SC001-SH010",
        "SC002-SH001",
        "SC002-SH002",
        "SC002-SH003",
        "SC002-SH004",
        "SC002-SH005",
        "SC002-SH006",
        "SC002-SH007",
        "SC002-SH008",
        "SC002-SH009",
        "SC002-SH010"
      ],
      "continuity_refs": [
        "PROP_BONE_FLUTE"
      ]
    },
    {
      "asset_id": "prop_qingming_register",
      "asset_type": "prop",
      "file_path": "assets/placeholders/prop_qingming_register.png",
      "status": "missing",
      "prompt_hint_zh": "清明院用于验名、追踪、错册和抹名的白册。",
      "prompt_hint_en": "Qingming white register used for name testing, tracking, false entries and erasure",
      "comfyui_role": "reference_image",
      "usage": [
        "SC002-SH001",
        "SC002-SH002",
        "SC002-SH003",
        "SC002-SH004",
        "SC002-SH005",
        "SC002-SH006",
        "SC002-SH007",
        "SC002-SH008",
        "SC002-SH009",
        "SC002-SH010"
      ],
      "continuity_refs": [
        "PROP_QINGMING_REGISTER"
      ]
    },
    {
      "asset_id": "prop_blood_record",
      "asset_type": "prop",
      "file_path": "assets/placeholders/prop_blood_record.png",
      "status": "missing",
      "prompt_hint_zh": "油纸包裹的残缺血牒，不可展开成万能圣物；它会引发追踪风险。",
      "prompt_hint_en": "oil-paper wrapped damaged blood record; not a magic solution, and it carries tracking risk",
      "comfyui_role": "reference_image",
      "usage": [
        "SC003-SH001",
        "SC003-SH002",
        "SC003-SH003",
        "SC003-SH004",
        "SC003-SH005",
        "SC003-SH006",
        "SC003-SH007",
        "SC003-SH008",
        "SC003-SH009",
        "SC003-SH010"
      ],
      "continuity_refs": [
        "PROP_BLOOD_RECORD"
      ]
    },
    {
      "asset_id": "prop_half_relay_token",
      "asset_type": "prop",
      "file_path": "assets/placeholders/prop_half_relay_token.png",
      "status": "missing",
      "prompt_hint_zh": "半枚日月驿令，只能触发断续旧驿残纹，不能完整开路或替代判断。",
      "prompt_hint_en": "half sun-moon relay token that only triggers broken old-route lines and cannot replace judgment",
      "comfyui_role": "reference_image",
      "usage": [
        "SC003-SH001",
        "SC003-SH002",
        "SC003-SH003",
        "SC003-SH004",
        "SC003-SH005",
        "SC003-SH006",
        "SC003-SH007",
        "SC003-SH008",
        "SC003-SH009",
        "SC003-SH010"
      ],
      "continuity_refs": [
        "PROP_HALF_RELAY_TOKEN"
      ]
    },
    {
      "asset_id": "prop_blood_salt_pouch",
      "asset_type": "prop",
      "file_path": "assets/placeholders/prop_blood_salt_pouch.png",
      "status": "missing",
      "prompt_hint_zh": "鹿弥与北境迁徙/求救线索道具。",
      "prompt_hint_en": "blood-salt pouch tied to Lu Mi and northern migration/rescue clues",
      "comfyui_role": "reference_image",
      "usage": [
        "SC003-SH001",
        "SC003-SH002",
        "SC003-SH003",
        "SC003-SH004",
        "SC003-SH005",
        "SC003-SH006",
        "SC003-SH007",
        "SC003-SH008",
        "SC003-SH009",
        "SC003-SH010"
      ],
      "continuity_refs": [
        "PROP_BLOOD_SALT_POUCH"
      ]
    }
  ]
}
